sanic_aredis-0.0.6.data/data/requirements/requirements.txt
sanic_aredis-0.0.6.data/data/requirements/requirements_dev.txt
sanic_aredis-0.0.6.data/data/requirements/requirements_test.txt
sanic_aredis-0.0.6.dist-info/DESCRIPTION.rst
sanic_aredis-0.0.6.dist-info/METADATA
sanic_aredis-0.0.6.dist-info/RECORD
sanic_aredis-0.0.6.dist-info/WHEEL
sanic_aredis-0.0.6.dist-info/metadata.json
sanic_aredis-0.0.6.dist-info/top_level.txt
sanic_redis/__init__.py
sanic_redis/broadcast.py
sanic_redis/cache.py
sanic_redis/namespace.py
sanic_redis/queue.py
sanic_redis/redis.py
sanic_redis/session.py
sanic_redis/standalone/__init__.py
sanic_redis/standalone/broadcast.py
sanic_redis/standalone/queue.py
