Metadata-Version: 2.0
Name: sanic-aredis
Version: 0.0.6
Summary: simple tools
Home-page: https://github.com/Sanic-Extensions/sanic-redis
Author: hsz
Author-email: hsz1273327@gmail.com
License: MIT
Provides-Extra: dev
Requires-Dist: recommonmark; extra == 'dev'
Requires-Dist: sphinx; extra == 'dev'
Requires-Dist: sphinxcontrib-napoleon; extra == 'dev'
Requires-Dist: wheel; extra == 'dev'
Provides-Extra: test
Requires-Dist: coverage; extra == 'test'
Requires-Dist: lxml; extra == 'test'
Requires-Dist: mypy; extra == 'test'
Requires-Dist: mypy-extensions; extra == 'test'
